odoo/addons/l10n_it_website_sale_corrispettivi/README.rst
odoo/addons/l10n_it_website_sale_corrispettivi/__init__.py
odoo/addons/l10n_it_website_sale_corrispettivi/__manifest__.py
odoo/addons/l10n_it_website_sale_corrispettivi/controllers/__init__.py
odoo/addons/l10n_it_website_sale_corrispettivi/controllers/main.py
odoo/addons/l10n_it_website_sale_corrispettivi/i18n/it.po
odoo/addons/l10n_it_website_sale_corrispettivi/i18n/l10n_it_website_sale_corrispettivi.pot
odoo/addons/l10n_it_website_sale_corrispettivi/models/__init__.py
odoo/addons/l10n_it_website_sale_corrispettivi/models/website.py
odoo/addons/l10n_it_website_sale_corrispettivi/readme/CONFIGURE.rst
odoo/addons/l10n_it_website_sale_corrispettivi/readme/CONTRIBUTORS.rst
odoo/addons/l10n_it_website_sale_corrispettivi/readme/DESCRIPTION.rst
odoo/addons/l10n_it_website_sale_corrispettivi/readme/ROADMAP.rst
odoo/addons/l10n_it_website_sale_corrispettivi/static/description/icon.png
odoo/addons/l10n_it_website_sale_corrispettivi/static/description/index.html
odoo/addons/l10n_it_website_sale_corrispettivi/tests/__init__.py
odoo/addons/l10n_it_website_sale_corrispettivi/tests/test_website_sale_no_corrispettivi.py
odoo/addons/l10n_it_website_sale_corrispettivi/views/templates.xml
odoo11_addon_l10n_it_website_sale_corrispettivi-11.0.1.0.0.99.dev5.dist-info/METADATA
odoo11_addon_l10n_it_website_sale_corrispettivi-11.0.1.0.0.99.dev5.dist-info/WHEEL
odoo11_addon_l10n_it_website_sale_corrispettivi-11.0.1.0.0.99.dev5.dist-info/top_level.txt
odoo11_addon_l10n_it_website_sale_corrispettivi-11.0.1.0.0.99.dev5.dist-info/RECORD
