Metadata-Version: 2.1
Name: odoo11-addon-l10n-it-website-sale-corrispettivi
Version: 11.0.1.0.0.99.dev5
Summary: Italian localization - Website Sale Corrispettivi
Home-page: https://github.com/OCA/l10n-italy/tree/11.0/l10n_it_website_sale_corrispettivi
Author: Agile Business Group,Odoo Community Association (OCA)
Author-email: support@odoo-community.org
License: AGPL-3
Platform: UNKNOWN
Classifier: Programming Language :: Python
Classifier: Framework :: Odoo
Classifier: Framework :: Odoo :: 11.0
Classifier: License :: OSI Approved :: GNU Affero General Public License v3
Requires-Python: >=2.7, !=3.0.*, !=3.1.*, !=3.2.*, !=3.3.*, !=3.4.*
Requires-Dist: odoo11-addon-l10n-it-corrispettivi-sale
Requires-Dist: odoo <11.1dev,>=11.0a
